nexus2srs/__init__.py
nexus2srs/__main__.py
nexus2srs/cli.py
nexus2srs/nexus2srs.py
nexus2srs-1.1.0.dist-info/licenses/LICENSE
nexus2srs-1.1.0.dist-info/METADATA
nexus2srs-1.1.0.dist-info/WHEEL
nexus2srs-1.1.0.dist-info/entry_points.txt
nexus2srs-1.1.0.dist-info/top_level.txt
nexus2srs-1.1.0.dist-info/RECORD
