Metadata-Version: 2.4
Name: nexus2srs
Version: 1.1.0
Summary: Program to convert NeXus (.nxs) scan Files to the classic ASCII SRS .dat files.
Author-email: Dan Porter <dan.porter@diamond.ac.uk>
Maintainer-email: Dan Porter <dan.porter@diamond.ac.uk>
License:                                  Apache License
Project-URL: Homepage, https://github.com/DiamondLightSource/nexus2srs
Project-URL: Documentation, https://github.com/DiamondLightSource/nexus2srs
Project-URL: Repository, https://github.com/DiamondLightSource/nexus2srs
Project-URL: Bug Tracker, https://github.com/DiamondLightSource/nexus2srs
Project-URL: Changelog, https://github.com/DiamondLightSource/nexus2srs/blob/master/README.md
Keywords: nexus
Classifier: Programming Language :: Python :: 3.10
Classifier: Intended Audience :: Science/Research
Classifier: Topic :: Scientific/Engineering :: Physics
Classifier: License :: OSI Approved :: Apache Software License
Classifier: Development Status :: 3 - Alpha
Requires-Python: >=3.10
License-File: LICENSE
Requires-Dist: numpy
Requires-Dist: h5py
Requires-Dist: hdf5plugin
Requires-Dist: hdfmap
Requires-Dist: pillow
Dynamic: license-file
